facebook_wda_plus-0.1.5.dist-info/licenses/AUTHORS
facebook_wda_plus-0.1.5.dist-info/licenses/LICENSE
wdap/__init__.py
wdap/_proto.py
wdap/exceptions.py
wdap/utils.py
wdap/xcui_element_types.py
wdap/usbmux/__init__.py
wdap/usbmux/exceptions.py
wdap/usbmux/pyusbmux.py
facebook_wda_plus-0.1.5.dist-info/METADATA
facebook_wda_plus-0.1.5.dist-info/WHEEL
facebook_wda_plus-0.1.5.dist-info/top_level.txt
facebook_wda_plus-0.1.5.dist-info/RECORD
