Metadata-Version: 2.4
Name: facebook-wda-plus
Version: 0.1.5
Summary: 基于 openatx/facebook-wda 升级改造的 iOS 自动化库，增强触摸动作等功能
Author-email: 太原湃森科技 <typaisenkeji@gmail.com>
License: MIT License
Project-URL: Homepage, https://github.com/paisenkeji/facebook-wda
Project-URL: Repository, https://github.com/paisenkeji/facebook-wda
Project-URL: Issues, https://github.com/paisenkeji/facebook-wda/issues
Project-URL: Documentation, https://github.com/paisenkeji/facebook-wda#readme
Classifier: Programming Language :: Python :: 3
Classifier: Programming Language :: Python :: 3.10
Classifier: Programming Language :: Python :: 3.11
Classifier: Programming Language :: Python :: 3.12
Classifier: Operating System :: OS Independent
Classifier: Topic :: Software Development :: Testing
Classifier: Topic :: Software Development :: Libraries :: Python Modules
Classifier: Intended Audience :: Developers
Requires-Python: >=3.10
License-File: LICENSE
License-File: AUTHORS
Requires-Dist: cached-property
Requires-Dist: construct
Requires-Dist: six
Requires-Dist: deprecated
Requires-Dist: retry
Requires-Dist: Pillow
Dynamic: license-file
